asgi_cgi/__init__.py
asgi_cgi/handler.py
asgi_cgi/py.typed
asgi_cgi/typing.py
asgi_cgi/utils.py
asgi_cgi/version.py
asgi_cgi_handler-0.0.1.dev1.dist-info/METADATA
asgi_cgi_handler-0.0.1.dev1.dist-info/WHEEL
asgi_cgi_handler-0.0.1.dev1.dist-info/top_level.txt
asgi_cgi_handler-0.0.1.dev1.dist-info/RECORD
