Metadata-Version: 2.1
Name: asgi-cgi-handler
Version: 0.0.1.dev1
Summary: run cgi scripts inside asgi
Home-page: https://github.com/synodriver/asgi-cgi-handler
Author: synodriver
Author-email: diguohuangjiajinweijun@gmail.com
Maintainer: synodriver
License: GPLv3
Keywords: asyncio,asgi,cgi
Platform: UNKNOWN
Classifier: Development Status :: 3 - Alpha
Classifier: Framework :: AsyncIO
Classifier: Operating System :: OS Independent
Classifier: License :: OSI Approved :: GNU General Public License v3 (GPLv3)
Classifier: Programming Language :: Python
Classifier: Programming Language :: Python :: 3.7
Classifier: Programming Language :: Python :: 3.8
Classifier: Programming Language :: Python :: 3.9
Classifier: Programming Language :: Python :: 3.10
Classifier: Programming Language :: Python :: Implementation :: CPython
Classifier: Programming Language :: Python :: Implementation :: PyPy
Requires-Python: >=3.8
Requires-Dist: starlette
Requires-Dist: h11
